kafkaproducerconsumer/KafkaTopics.py
kafkaproducerconsumer/__init__.py
kafkaproducerconsumer-0.0.5.dist-info/LICENSE
kafkaproducerconsumer-0.0.5.dist-info/METADATA
kafkaproducerconsumer-0.0.5.dist-info/WHEEL
kafkaproducerconsumer-0.0.5.dist-info/top_level.txt
kafkaproducerconsumer-0.0.5.dist-info/RECORD
